[
    {
        "name": "trailer",
        "class": 4,
        "confidence": 0.6510635018348694,
        "box": {
            "x1": 74.95849609375,
            "y1": 270.27886962890625,
            "x2": 380.7088623046875,
            "y2": 500.47222900390625
        },
        "datetime": "2023-07-09 23:17:28.627704"
    }
][
    {
        "name": "trailer",
        "class": 4,
        "confidence": 0.7006053924560547,
        "box": {
            "x1": 75.4578857421875,
            "y1": 271.4935302734375,
            "x2": 382.9048156738281,
            "y2": 500.23931884765625
        },
        "datetime": "23:20:07"
    }
][
    {
        "name": "blue_wheel",
        "class": 0,
        "confidence": 0.8473791480064392,
        "box": {
            "x1": 413.92449951171875,
            "y1": 344.0880432128906,
            "x2": 522.8709716796875,
            "y2": 452.2746887207031
        },
        "datetime": "23:22:01"
    }
]